[
  {
    "id": 1,
    "category": "Работа и деньги",
    "question": "Как ты думаешь, какие твои недостатки сказываются на работе?"
  },
  {
    "id": 2,
    "category": "Работа и деньги",
    "question": "Ты можешь зарабатывать 10 000$ месяц? Почему тебе это легко/сложно представить?"
  },
  {
    "id": 3,
    "category": "Работа и деньги",
    "question": "Есть ли связь между уровнем заработка и либидо человека? Мужчины? Женщины?"
  },
  {
    "id": 4,
    "category": "Работа и деньги",
    "question": "Какой процент от заработка ты откладываешь в качестве сбережений? На что ты откладываешь?"
  },
  {
    "id": 5,
    "category": "Работа и деньги",
    "question": "Что тебе не нравится в твоей карьере и где ты считаешь ты потратил(а)/тратишь время зря?"
  },
  {
    "id": 6,
    "category": "Работа и деньги",
    "question": "Есть ли взаимосвязь между уровнем любви и стоимостью подарков? Почему так?"
  }
]
